codespeak/.DS_Store
codespeak/__init__.py
codespeak/apis/api_metadata.py
codespeak/apis/get_api_key.py
codespeak/constants.py
codespeak/decorate/writable.py
codespeak/frame.py
codespeak/frame_tests.py
codespeak/function/__init__.py
codespeak/function/function_attributes.py
codespeak/function/function_declaration.py
codespeak/function/function_declaration_lite.py
codespeak/function/function_lite.py
codespeak/function/function_manager.py
codespeak/function/helper_types/make_inference_response.py
codespeak/function/writable_function.py
codespeak/helpers/__init__.py
codespeak/helpers/align.py
codespeak/helpers/auto_detect_abspath_to_project_root.py
codespeak/helpers/derive_module_qualname_for_object.py
codespeak/helpers/extract_delimited_python_code_from_string.py
codespeak/helpers/gather_arguments.py
codespeak/helpers/get_attr_from_qualname.py
codespeak/helpers/get_definitions_from_function_object.py
codespeak/helpers/guarantee_abspath_to_root_exists.py
codespeak/helpers/self_type.py
codespeak/helpers/set_attr_for_qualname.py
codespeak/helpers/try_get_self_definition_for_for_inferred_function.py
codespeak/inference/codespeak_service.py
codespeak/inference/inference_engine.py
codespeak/inference/make_inference_response.py
codespeak/inference/replace_function.py
codespeak/inference/test_transform.py
codespeak/inference/transform_inference.py
codespeak/interactive_mode/get_approval.py
codespeak/module_frame.py
codespeak/public/dot_get.py
codespeak/public/inferred_exception.py
codespeak/public/rest_requests/delete.py
codespeak/public/rest_requests/get.py
codespeak/public/rest_requests/post.py
codespeak/public/rest_requests/put.py
codespeak/public/rest_requests/request.py
codespeak/public/rest_requests/rest_request_helpers.py
codespeak/settings.py
codespeak/test_function.py
codespeak/type_definitions/classify.py
codespeak/type_definitions/free_modules.py
codespeak/type_definitions/import_definition.py
codespeak/type_definitions/type_definition.py
codespeak-0.1.7.dist-info/METADATA
codespeak-0.1.7.dist-info/WHEEL
codespeak-0.1.7.dist-info/RECORD
