Metadata-Version: 2.1
Name: codespeak
Version: 0.1.7
Summary: 
Author: nateshirley
Author-email: nate.00.shirley@gmail.com
Requires-Python: >=3.10,<4.0
Classifier: Programming Language :: Python :: 3
Classifier: Programming Language :: Python :: 3.10
Classifier: Programming Language :: Python :: 3.11
Requires-Dist: astor (>=0.8.1,<0.9.0)
Requires-Dist: furl (>=2.1.3,<3.0.0)
Requires-Dist: httpx (>=0.24.1,<0.25.0)
Requires-Dist: libcst (>=1.0.1,<2.0.0)
Requires-Dist: openai (>=0.27.6,<0.28.0)
Requires-Dist: pydantic (>=1.10.7,<2.0.0)
Requires-Dist: pytest (>=7.3.1,<8.0.0)
Requires-Dist: python-dotenv (>=1.0.0,<2.0.0)
Requires-Dist: sqlalchemy (>=2.0.13,<3.0.0)
